merge_spreadsheets-0.0.2.dist-info/DESCRIPTION.rst
merge_spreadsheets-0.0.2.dist-info/METADATA
merge_spreadsheets-0.0.2.dist-info/RECORD
merge_spreadsheets-0.0.2.dist-info/WHEEL
merge_spreadsheets-0.0.2.dist-info/entry_points.txt
merge_spreadsheets-0.0.2.dist-info/metadata.json
merge_spreadsheets-0.0.2.dist-info/top_level.txt
src/__init__.py
src/gui_merge_spreadsheets.py
src/spreadsheets.py
tests/__init__.py
tests/example.xlsx
tests/test_spreadsheets.py
