Metadata-Version: 2.0
Name: merge-spreadsheets
Version: 0.0.2
Summary: UNKNOWN
Home-page: UNKNOWN
Author: msBooM
Author-email: work-msboom@yandex.ru
License: UNKNOWN
Platform: UNKNOWN
Requires-Dist: openpyxl
